Workbook

Sheet Asumsi
A1: ASUMSI
A2: Parameter | B2: Nilai | C2: Keterangan
A3: Hari Kerja per Bulan | B3: 26 | C3: Hari kerja efektif UMKM, tidak termasuk hari dimana UMKM tersebut libur
A4: Bulan dalam 1 Tahun | B4: 12 | C4: Untuk konversi permintaan bulanan menjadi permintaan tahunan untuk menyesuaikan inventori yang dibutuhkan

Sheet Penjelasan
A1: Komponen | B1: Penjelasan | C1: Contoh
A2: Biaya Tetap | B2: Biaya yang harus dibayar meskipun tidak ada penjualan. | C2: Sewa tempat, gaji karyawan tetap, listrik dasar
A3: Biaya Variabel | B3: Biaya yang berubah sesuai jumlah produksi/penjualan. | C3: Biji Kopi, Gula, Susu
A4: Biaya Tidak Langsung | B4: Biaya yang mendukung operasional tapi tidak langsung terkait produksi satu unit barang. | C4: Biaya kebersihan, administrasi, peralatan kantor,

Sheet Panduan Teknis
A1: CATATAN PENTING (WAJIB DIBACA)
A2: 1. | B2: Seluruh angka pada sheet Fixed Cost, Variable Cost, Overhead Cost, Inventori, dan Cash Flow saat ini adalah DATA DUMMY/CONTOH untuk menguji struktur rumus - BUKAN data riil UMKM.
A3: 2 | B3: Model EOQ mengasumsikan permintaan relatif stabil. Untuk UMKM dengan permintaan sangat fluktuatif (mis. musim wisata ramai vs sepi), bandingkan hasil pada Sheet Inventori Fix atau Inventori Harian menggunakan metode EOQ dan Metode LFL, lalu pilih yang paling sesuai kondisi lapangan.
A4: 3 | B4: Safety Stock di Sheet Inventori merujuk pada stok yang akan disimpan untuk jaga jaga pada UMKM
A5: 4 | B5: Alokasi Fixed Cost dan Overhead ke tiap produk pada sheet Arus Kas memakai persentase yang HARUS diisi manual sesuai estimasi pemilik UMKM (mis. berdasarkan proporsi waktu produksi atau volume produksi).
A7: KODE WARNA SEL
A8: Biru | B8: Angka yang boleh diubah
A9: Hitam | B9: Hasil perhitungan
A10: Hijau | B10: Data referensi lain dari sheet lain
A11: Kuning (latar) | B11: Asumsi yang perlu diperhatikan
A14: DAFTAR SHEET
A15: Asumsi | B15: Parameter umum (hari kerja/bulan) yang dipakai formula di sheet lain
A16: Fixed Cost | B16: Biaya tetap bulanan (sewa, gaji tetap, penyusutan, dst)
A17: Variable Cost | B17: Biaya bahan/komponen per unit produk
A18: Overhead Cost | B18: Biaya operasional pendukung (listrik, air, transportasi, kemasan)
A19: Inventori | B19: Model EOQ+Safety Stock dan LFL+Safety Stock per bahan baku
A20: Cash Flow & Profit | B20: Revenue, total cost, profit, dan margin bulanan per produk
A21: Dashboard | B21: Ringkasan visual seluruh sheet

Sheet Biaya Tetap
A1: FIXED COST BULANAN
A2: No | B2: Kategori | C2: Nominal per Bulan (Rp) | D2: Catatan
A3: 1 | B3: Sewa Tempat/Lahan Usaha | C3: 500000 | D3: Isi - jika sudah menjadi hak milik dan tidak ada pengeluaran rutin bulanan tentang ini
A4: 2 | B4: Gaji Karyawan Tetap | C4: 0 | D4: Isi jika ada karyawan tetap dan kosongkan/0 jika belum ada
A5: 3 | B5: Penyusutan Peralatan | C5: 100000 | D5: Nilai peralatan / estimasi umur ekonomis, per bulan
A6: 4 | B6: Izin Usaha / Pajak Tetap | D6: PBB, retribusi, dsb bila ada
A7: TOTAL FIXED COST | C7: =SUM(C3:C6) -> 600000

Sheet Biaya Variabel
A1: VARIABLE COST PER UNIT PRODUK | I1: RINGKASAN TOTAL VARIABLE COST PER PRODUK
A2: No | B2: Nama Produk | C2: Nama Bahan/Komponen | D2: Satuan | E2: Kuantitas per Unit | F2: Harga per Satuan (Rp) | G2: Biaya per Unit (Rp) | I2: Nama Produk | J2: Total Variable Cost per Unit (Rp)
A3: 1 | B3: Produk A | C3: Bahan Baku Utama | D3: kg | E3: 0.2 | F3: 15000 | G3: =E3*F3 -> 3000 | I3: Produk A | J3: =SUMIF($B$3:$B$8,I3,$G$3:$G$8) -> 6000
A4: 2 | B4: Produk A | C4: Bahan Pendukung | D4: pcs | E4: 1 | F4: 2000 | G4: =E4*F4 -> 2000 | I4: Produk B | J4: =SUMIF($B$3:$B$8,I4,$G$3:$G$8) -> 6450
A5: 3 | B5: Produk A | C5: Kemasan Primer | D5: pcs | E5: 1 | F5: 1000 | G5: =E5*F5 -> 1000
A6: 4 | B6: Produk B | C6: Bahan Baku Utama | D6: kg | E6: 0.15 | F6: 15000 | G6: =E6*F6 -> 2250
A7: 5 | B7: Produk B | C7: Bahan Pendukung | D7: pcs | E7: 2 | F7: 1500 | G7: =E7*F7 -> 3000
A8: 6 | B8: Produk B | C8: Kemasan Primer | D8: pcs | E8: 1 | F8: 1200 | G8: =E8*F8 -> 1200

Sheet Biaya Tidak Langsung 
A1: OVERHEAD COST BULANAN
A2: No | B2: Kategori | C2: Nominal per Bulan (Rp) | D2: % Alokasi ke Produksi | E2: Overhead Teralokasi (Rp)
A3: 1 | B3: Listrik | C3: 300000 | D3: 0.7 | E3: =C3*D3 -> 210000
A4: 2 | B4: Air | C4: 100000 | D4: 0.5 | E4: =C4*D4 -> 50000
A5: 3 | B5: Transportasi/Distribusi | C5: 200000 | D5: 1 | E5: =C5*D5 -> 200000
A6: 4 | B6: Kemasan Sekunder & Packing | C6: 150000 | D6: 1 | E6: =C6*D6 -> 150000
A7: TOTAL OVERHEAD TERALOKASI | E7: =SUM(E3:E6) -> 610000

Sheet Inventori Harian
A1: INVENTORI - MODEL EOQ + SAFETY STOCK vs LFL + SAFETY STOCK
A2: DATA INPUT (isi dari hasil wawancara UMKM) | L2: HELPER (perhitungan harian) | S2: MODEL LFL + SAFETY STOCK
A3: No | B3: Nama Barang/Bahan Baku | C3: Satuan | D3: Permintaan Rata-rata/Bulan (unit) | E3: Permintaan Maksimum/Bulan (unit) | F3: Lead Time Rata-rata (hari) | G3: Lead Time Maksimum (hari) | H3: Biaya Pemesanan per Order (Rp) | I3: Biaya Simpan per Unit/Bulan (Rp) | J3: Harga Beli per Unit (Rp) | K3: Stok Saat Ini (unit) | L3: Permintaan Harian Rata-rata | M3: Permintaan Harian Maksimum | N3: Permintaan Tahunan (D) | O3: EOQ (unit/order) | P3: Safety Stock (unit) | Q3: Reorder Point (unit) | R3: Status Reorder | S3: Kebutuhan Bulan Depan (unit) | T3: Safety Stock LFL (unit) | U3: Jumlah Pesan (unit) | V3: Status Reorder
A4: 1 | B4: Bahan Baku A (contoh) | C4: kg | D4: 60 | E4: 100 | F4: 5 | G4: 10 | H4: 50000 | I4: 500 | J4: 15000 | K4: 40 | L4: =D4/[1]Asumsi!$C$4 -> 2.3076923 | M4: =E4/[1]Asumsi!$C$4 -> 3.8461538 | N4: =D4*[1]Asumsi!$C$5 -> 720 | O4: =ROUND(SQRT(2*N4*H4/(I4*[1]Asumsi!$C$5)),0) -> 110 | P4: =ROUND((M4-L4)*G4,0) -> 15 | Q4: =ROUND(L4*F4+P4,0) -> 27 | R4: =IF(K4<=Q4,"Segera Pesan","Aman") -> Aman | S4: =D4 -> 60 | T4: =P4 -> 15 | U4: =MAX(S4+T4-K4,0) -> 35 | V4: =IF(K4<S4+T4,"Segera Pesan","Aman") -> Segera Pesan
A5: 2 | B5: Bahan Baku B (contoh) | C5: pcs | D5: 200 | E5: 350 | F5: 3 | G5: 7 | H5: 30000 | I5: 150 | J5: 2000 | K5: 150 | L5: =D5/[1]Asumsi!$C$4 -> 7.6923077 | M5: =E5/[1]Asumsi!$C$4 -> 13.461538 | N5: =D5*[1]Asumsi!$C$5 -> 2400 | O5: =ROUND(SQRT(2*N5*H5/(I5*[1]Asumsi!$C$5)),0) -> 283 | P5: =ROUND((M5-L5)*G5,0) -> 40 | Q5: =ROUND(L5*F5+P5,0) -> 63 | R5: =IF(K5<=Q5,"Segera Pesan","Aman") -> Aman | S5: =D5 -> 200 | T5: =P5 -> 40 | U5: =MAX(S5+T5-K5,0) -> 90 | V5: =IF(K5<S5+T5,"Segera Pesan","Aman") -> Segera Pesan
A6: 3 | B6: Bahan Baku C (contoh) | C6: pcs | D6: 150 | E6: 260 | F6: 4 | G6: 8 | H6: 25000 | I6: 200 | J6: 1000 | K6: 80 | L6: =D6/[1]Asumsi!$C$4 -> 5.7692308 | M6: =E6/[1]Asumsi!$C$4 -> 10 | N6: =D6*[1]Asumsi!$C$5 -> 1800 | O6: =ROUND(SQRT(2*N6*H6/(I6*[1]Asumsi!$C$5)),0) -> 194 | P6: =ROUND((M6-L6)*G6,0) -> 34 | Q6: =ROUND(L6*F6+P6,0) -> 57 | R6: =IF(K6<=Q6,"Segera Pesan","Aman") -> Aman | S6: =D6 -> 150 | T6: =P6 -> 34 | U6: =MAX(S6+T6-K6,0) -> 104 | V6: =IF(K6<S6+T6,"Segera Pesan","Aman") -> Segera Pesan

Sheet Inventori Mingguan
A1: Minggu | B1: 1 | C1: 2 | D1: 3 | E1: 4 | F1: 5 | G1: 6 | H1: 7 | I1: 8 | J1: 9 | K1: 10 | L1: 11 | M1: 12
A2: Kuantitas/Banyaknya | B2: 150 | C2: 200 | D2: 100 | E2: 250 | F2: 200 | G2: 300 | H2: 200 | I2: 150 | J2: 350 | K2: 200 | L2: 100 | M2: 400
A4: Minggu | B4: 0 | C4: 1 | D4: 2 | E4: 3 | F4: 4 | G4: 5 | H4: 6 | I4: 7 | J4: 8 | K4: 9 | L4: 10 | M4: 11 | N4: 12 | P4: Total Gross Requirements | Q4: =SUM(B5:N5) -> 2600
A5: Kebutuhan Total | C5: =B2 -> 150 | D5: =C2 -> 200 | E5: =D2 -> 100 | F5: =E2 -> 250 | G5: =F2 -> 200 | H5: =G2 -> 300 | I5: =H2 -> 200 | J5: =I2 -> 150 | ... N5: =M2 -> 400 | P5: Avarage T. Gross Requirements | Q5: =ROUNDUP(AVERAGE(C5:N5),0) -> 217
A6: Barang Masuk Terjadwal | P6: D (Avarage x 52) | Q6: =Q5*52 -> 11284
A7: Stok yang Ada | B7: 100 | C7: =C9-C8 -> 74 | D7: =D9-D8 -> 60 | E7: =E9-E8 -> 53 | F7: =F9-F8 -> 51 | G7: =G9-G8 -> 68 | H7: =H9-H8 -> 47 | I7: =I9-I8 -> 64 | J7: =J9-J8 -> 69 | ... N7: =N9-N8 -> 73 | P7: S | Q7: 25
A8: Kebutuhan Bersih | C8: =C5-B7 -> 50 | D8: =D5-C7 -> 126 | E8: =E5-D7 -> 40 | F8: =F5-E7 -> 197 | G8: =G5-F7 -> 149 | H8: =H5-G7 -> 232 | I8: =I5-H7 -> 153 | J8: =J5-I7 -> 86 | ... N8: =N5-M7 -> 330 | P8: H (Holding Cost x 52) | Q8: =B14*52 -> 624
A9: Pesanan Masuk Direncanakan | C9: =ROUNDUP((C8+$B$13)/$Q$9,0)*$Q$9 -> 124 | D9: =ROUNDUP((D8+$B$13)/$Q$9,0)*$Q$9 -> 186 | E9: =ROUNDUP((E8+$B$13)/$Q$9,0)*$Q$9 -> 93 | F9: =ROUNDUP((F8+$B$13)/$Q$9,0)*$Q$9 -> 248 | G9: =ROUNDUP((G8+$B$13)/$Q$9,0)*$Q$9 -> 217 | H9: =ROUNDUP((H8+$B$13)/$Q$9,0)*$Q$9 -> 279 | I9: =ROUNDUP((I8+$B$13)/$Q$9,0)*$Q$9 -> 217 | J9: =ROUNDUP((J8+$B$13)/$Q$9,0)*$Q$9 -> 155 | ... N9: =ROUNDUP((N8+$B$13)/$Q$9,0)*$Q$9 -> 403 | P9: Q* | Q9: =ROUNDUP(SQRT(2*Q6*Q7/Q8),0) -> 31
A10: Pesanan Dibuat ke Supplier Segera | B10: =E9 -> 93 | C10: 248 | D10: 186 | E10: 310 | F10: 186 | G10: 155 | H10: 372 | I10: 186 | J10: 93 | K10: 403 | P10: Lead Time (minggu) | Q10: 3
A11: Status Reorder | B11: =IF(B7<$Q$12,"Segera Pesan") -> Segera Pesan | C11: =IF(C7<$Q$12,"Segera Pesan") -> Segera Pesan | D11: =IF(D7<$Q$12,"Segera Pesan") -> Segera Pesan | E11: =IF(E7<$Q$12,"Segera Pesan") -> Segera Pesan | F11: =IF(F7<$Q$12,"Segera Pesan") -> Segera Pesan | G11: =IF(G7<$Q$12,"Segera Pesan") -> Segera Pesan | H11: =IF(H7<$Q$12,"Segera Pesan") -> Segera Pesan | I11: =IF(I7<$Q$12,"Segera Pesan") -> Segera Pesan | ... N11: =IF(N7<$Q$12,"Segera Pesan") -> Segera Pesan | P11: Stok Saat Ini (unit) | Q11: 50
A12: Waktu Tunggu : | B12: 3 | C12: minggu | P12: Reorder Point (ROP) | Q12: =Q5*B12+B13 -> 696
A13: Stok Jaga Jaga : | B13: 45 | C13: Units per minggu
A14: Biaya Menyimpan : | B14: 12 | C14: per unit per minggu
A15: Biaya Mesin : | B15: 25 | C15: untuk setiap pesanan
A17: Total biaya simpan: | B17: =B14*SUM(C7:N7) -> 8820
A18: Total biaya mesin: | B18: =B15*(COUNT(B9:N9)-B12) -> 225
A19: Total biaya : | B19: =B17+B18 -> 9045
A21: Minggu | B21: 1 | C21: 2 | D21: 3 | E21: 4 | F21: 5 | G21: 6 | H21: 7 | I21: 8 | J21: 9 | K21: 10 | L21: 11 | M21: 12
A22: Kuantitas/Banyaknya | B22: 150 | C22: 200 | D22: 100 | E22: 250 | F22: 200 | G22: 300 | H22: 200 | I22: 150 | J22: 350 | K22: 200 | L22: 100 | M22: 400
A24: Minggu | B24: 0 | C24: 1 | D24: 2 | E24: 3 | F24: 4 | G24: 5 | H24: 6 | I24: 7 | J24: 8 | K24: 9 | L24: 10 | M24: 11 | N24: 12
A25: Kebutuhan Total | C25: =B22 -> 150 | D25: =C22 -> 200 | E25: =D22 -> 100 | F25: =E22 -> 250 | G25: =F22 -> 200 | H25: =G22 -> 300 | I25: =H22 -> 200 | J25: =I22 -> 150 | ... N25: =M22 -> 400
A26: Barang Masuk Terjadwal
A27: Stok yang Ada | B27: 50 | C27: =B27+B26+C28-C25+$B$33 -> 45 | D27: =C27+C26+D28-D25+$B$33 -> 45 | E27: =D27+D26+E28-E25+$B$33 -> 45 | F27: =E27+E26+F28-F25+$B$33 -> 45 | G27: =F27+F26+G28-G25+$B$33 -> 45 | H27: =G27+G26+H28-H25+$B$33 -> 45 | I27: =H27+H26+I28-I25+$B$33 -> 45 | J27: =I27+I26+J28-J25+$B$33 -> 45 | ... N27: =M27+M26+N28-N25+$B$33 -> 45
A28: Kebutuhan Bersih | C28: =C25-B27 -> 100 | D28: =D25-C27 -> 155 | E28: =E25-D27 -> 55 | F28: =F25-E27 -> 205 | G28: =G25-F27 -> 155 | H28: =H25-G27 -> 255 | I28: =I25-H27 -> 155 | J28: =J25-I27 -> 105 | ... N28: =N25-M27 -> 355
A29: Pesanan Masuk Direncanakan | C29: =C28+C27 -> 145 | D29: =D28+D27 -> 200 | E29: =E28+E27 -> 100 | F29: =F28+F27 -> 250 | G29: =G28+G27 -> 200 | H29: =H28+H27 -> 300 | I29: =I28+I27 -> 200 | J29: =J28+J27 -> 150 | ... N29: =N28+N27 -> 400
A30: Pesanan Dibuat ke Supplier Segera | B30: =E29 -> 100 | C30: =F29 -> 250 | D30: =G29 -> 200 | E30: =H29 -> 300 | F30: =I29 -> 200 | G30: =J29 -> 150 | H30: =K29 -> 350 | I30: =L29 -> 200 | ... N30: =Q29 -> 0
A31: Status Reorder | B31: =IF(B28>0,"Segera Pesan") -> FALSE | C31: =IF(C28>0,"Segera Pesan") -> Segera Pesan | D31: =IF(D28>0,"Segera Pesan") -> Segera Pesan | E31: =IF(E28>0,"Segera Pesan") -> Segera Pesan | F31: =IF(F28>0,"Segera Pesan") -> Segera Pesan | G31: =IF(G28>0,"Segera Pesan") -> Segera Pesan | H31: =IF(H28>0,"Segera Pesan") -> Segera Pesan | I31: =IF(I28>0,"Segera Pesan") -> Segera Pesan | ... N31: =IF(N28>0,"Segera Pesan") -> Segera Pesan
A32: Waktu Tunggu : | B32: 3 | C32: week
A33: Stok Jaga Jaga : | B33: 45 | C33: units per week
A34: Biaya Menyimpan : | B34: 12 | C34: per unit per week
A35: Biaya Mesin : | B35: 25 | C35: for each order
A37: Total biaya simpan: | B37: =B34*SUM(C27:N27) -> 6480
A38: Total biaya mesin: | B38: =B35*(COUNT(B29:N29)-B32) -> 225
A39: Total biaya : | B39: =B37+B38 -> 6705

Sheet Arus Kas
A1: CASH FLOW & PROFIT BULANAN PER PRODUK
A2: Bulan | B2: Nama Produk | C2: Unit Terjual | D2: Harga Jual per Unit (Rp) | E2: Revenue (Rp) | F2: Variable Cost/Unit (Rp) | G2: Total Variable Cost (Rp) | H2: % Alokasi Fixed Cost | I2: Alokasi Fixed Cost (Rp) | J2: % Alokasi Overhead | K2: Alokasi Overhead (Rp) | L2: Total Cost (Rp) | M2: Profit (Rp) | N2: Profit Margin (%)
A3: Bulan 1 | B3: Produk A | C3: 300 | D3: 25000 | E3: =C3*D3 -> 7500000 | F3: =VLOOKUP(B3,'Biaya Variabel'!$I$2:$J$4,2) -> 6000 | G3: =C3*F3 -> 1800000 | H3: 0.6 | I3: ='Biaya Tetap'!$C$7*H3 -> 360000 | J3: 0.6 | K3: ='Biaya Tidak Langsung '!$E$7*J3 -> 366000 | L3: =G3+I3+K3 -> 2526000 | M3: =E3-L3 -> 4974000 | N3: =IF(E3=0,0,M3/E3) -> 0.6632
A4: Bulan 1 | B4: Produk B | C4: 250 | D4: 18000 | E4: =C4*D4 -> 4500000 | F4: =VLOOKUP(B4,'Biaya Variabel'!$I$2:$J$4,2) -> 6450 | G4: =C4*F4 -> 1612500 | H4: 0.4 | I4: ='Biaya Tetap'!$C$7*H4 -> 240000 | J4: 0.4 | K4: ='Biaya Tidak Langsung '!$E$7*J4 -> 244000 | L4: =G4+I4+K4 -> 2096500 | M4: =E4-L4 -> 2403500 | N4: =IF(E4=0,0,M4/E4) -> 0.53411111
A5: Bulan 2 | B5: Produk A | C5: 320 | D5: 25000 | E5: =C5*D5 -> 8000000 | F5: =VLOOKUP(B5,'Biaya Variabel'!$I$2:$J$4,2) -> 6000 | G5: =C5*F5 -> 1920000 | H5: 0.55 | I5: ='Biaya Tetap'!$C$7*H5 -> 330000 | J5: 0.55 | K5: ='Biaya Tidak Langsung '!$E$7*J5 -> 335500 | L5: =G5+I5+K5 -> 2585500 | M5: =E5-L5 -> 5414500 | N5: =IF(E5=0,0,M5/E5) -> 0.6768125
A6: Bulan 2 | B6: Produk B | C6: 260 | D6: 18000 | E6: =C6*D6 -> 4680000 | F6: =VLOOKUP(B6,'Biaya Variabel'!$I$2:$J$4,2) -> 6450 | G6: =C6*F6 -> 1677000 | H6: 0.45 | I6: ='Biaya Tetap'!$C$7*H6 -> 270000 | J6: 0.45 | K6: ='Biaya Tidak Langsung '!$E$7*J6 -> 274500 | L6: =G6+I6+K6 -> 2221500 | M6: =E6-L6 -> 2458500 | N6: =IF(E6=0,0,M6/E6) -> 0.52532051
A8: Total | E8: =SUM(E3:E6) -> 24680000 | G8: =SUM(G3:G6) -> 7009500 | I8: =SUM(I3:I6) -> 1200000 | K8: =SUM(K3:K6) -> 1220000 | L8: =SUM(L3:L6) -> 9429500 | M8: =SUM(M3:M6) -> 15250500

Sheet Visualisasi
B2: DASHBOARD RINGKASAN UMKM
B4: RINGKASAN BIAYA BULANAN
B5: Komponen | C5: Nominal (Rp)
B6: Total Fixed Cost | C6: ='Biaya Tetap'!C7 -> 600000
B7: Total Overhead Teralokasi | C7: ='Biaya Tidak Langsung '!E7 -> 610000
B8: Total Variable Cost (bulan berjalan) | C8: ='Arus Kas'!G8 -> 7009500
B10: RINGKASAN PROFIT BULANAN
B11: Komponen | C11: Nominal (Rp)
B12: Total Revenue | C12: ='Arus Kas'!E8 -> 24680000
B13: Total Cost | C13: ='Arus Kas'!L8 -> 9429500
B14: Total Profit | C14: =C12-C13 -> 15250500
B16: Profit Margin Rata-rata | C16: =IF(C12=0,0,C14/C12) -> 0.6179295
B18: STATUS REORDER INVENTORI
B19: Perlu Segera Pesan (Model EOQ) | C19: =COUNTIF('Inventori Mingguan'!B11:N11,"Segera Pesan") -> 13
B20: Perlu Segera Pesan (Model LFL) | C20: =COUNTIF('Inventori Mingguan'!B31:N31,"Segera Pesan") -> 12
